AUTHORS.rst
CONTRIBUTING.rst
HISTORY.rst
LICENSE
MANIFEST.in
README.rst
setup.cfg
setup.py
Appengine_Fixture_Loader.egg-info/PKG-INFO
Appengine_Fixture_Loader.egg-info/SOURCES.txt
Appengine_Fixture_Loader.egg-info/dependency_links.txt
Appengine_Fixture_Loader.egg-info/not-zip-safe
Appengine_Fixture_Loader.egg-info/top_level.txt
appengine_fixture_loader/__init__.py
appengine_fixture_loader/loader.py
docs/Makefile
docs/authors.rst
docs/conf.py
docs/contributing.rst
docs/history.rst
docs/index.rst
docs/installation.rst
docs/make.bat
docs/readme.rst
docs/usage.rst
tests/__init__.py
tests/ancestor_tests.py
tests/ancestors_and_dogs.json
tests/hard_coded_id.json
tests/hard_coded_id_test.py
tests/multi_kind_tests.py
tests/multi_level_tests.py
tests/persons.json
tests/persons_and_dogs.json
tests/persons_children_and_dogs.json
tests/single_level_tests.py