Metadata-Version: 1.1
Name: Appengine-Fixture-Loader
Version: 0.1.9
Summary: Appengine fixture loader
Home-page: http://github.com/rbanffy/appengine-fixture-loader/
Author: Ricardo Bánffy
Author-email: appengine-fixture-loader@autonomic.com.br
License: Apache
Keywords: appengine,loader,fixture
Platform: UNKNOWN
Classifier: Development Status :: 2 - Pre-Alpha
Classifier: Environment :: Web Environment
Classifier: Intended Audience :: Developers
Classifier: License :: OSI Approved :: Apache Software License
Classifier: Natural Language :: English
Classifier: Operating System :: OS Independent
Classifier: Programming Language :: Python :: 2.7
Classifier: Programming Language :: Python
Classifier: Topic :: Internet :: WWW/HTTP :: Dynamic Content
Classifier: Topic :: Software Development :: Libraries :: Python Modules
